idr/__init__.py
idr/attributes.py
idr/connections.py
idr/externalDBs.py
idr/images.py
idr/visualizations.py
idr/widgets.py
idr/tests/__init__.py
idr/tests/config.py
idr/tests/test_attributes.py
idr/tests/test_externalDBs.py
idr/tests/test_visualizations.py
idr/tests/test_widgets.py
idr_py-0.4.2.dist-info/METADATA
idr_py-0.4.2.dist-info/WHEEL
idr_py-0.4.2.dist-info/top_level.txt
idr_py-0.4.2.dist-info/RECORD
